mini_vllm/__init__.py
mini_vllm/block_manager.py
mini_vllm/llm_engine.py
mini_vllm/model.py
mini_vllm/sampler.py
mini_vllm/scheduler.py
mini_vllm/sequence.py
mini_vllm/kernels/__init__.py
mini_vllm/kernels/attention.py
mini_vllm-0.1.1.dist-info/METADATA
mini_vllm-0.1.1.dist-info/WHEEL
mini_vllm-0.1.1.dist-info/licenses/LICENSE
mini_vllm-0.1.1.dist-info/RECORD
