Metadata-Version: 2.4
Name: mini-vllm
Version: 0.1.1
Summary: An educational implementation of an inference engine
Author: Umang Kaushik
License: MIT
License-File: LICENSE
Keywords: inference,llm,paged-attention,vllm
Requires-Python: >=3.12
Requires-Dist: dotenv>=0.9.9
Requires-Dist: einops>=0.8.1
Requires-Dist: huggingface-hub>=0.36.0
Requires-Dist: modal>=1.2.5
Requires-Dist: numpy>=2.3.5
Requires-Dist: pytest>=9.0.2
Requires-Dist: torch>=2.9.1
Requires-Dist: transformers>=4.57.3
Requires-Dist: triton>=3.5.1
